luftdatenpumpe/__init__.py
luftdatenpumpe/commands.py
luftdatenpumpe/engine.py
luftdatenpumpe/geo.py
luftdatenpumpe/util.py
luftdatenpumpe/grafana/__init__.py
luftdatenpumpe/grafana/dashboard-map.json
luftdatenpumpe/grafana/dashboard-trend.json
luftdatenpumpe/grafana/datasource-influxdb.json
luftdatenpumpe/grafana/datasource-weatherbase.json
luftdatenpumpe/source/__init__.py
luftdatenpumpe/source/common.py
luftdatenpumpe/source/eea.py
luftdatenpumpe/source/irceline.py
luftdatenpumpe/source/luftdaten_info.py
luftdatenpumpe/source/openaq.py
luftdatenpumpe/source/rdbms.py
luftdatenpumpe/target/__init__.py
luftdatenpumpe/target/influxdb.py
luftdatenpumpe/target/json.py
luftdatenpumpe/target/mqtt.py
luftdatenpumpe/target/rdbms.py
luftdatenpumpe/target/stream.py
luftdatenpumpe-0.21.1.dist-info/LICENSE
luftdatenpumpe-0.21.1.dist-info/METADATA
luftdatenpumpe-0.21.1.dist-info/WHEEL
luftdatenpumpe-0.21.1.dist-info/entry_points.txt
luftdatenpumpe-0.21.1.dist-info/top_level.txt
luftdatenpumpe-0.21.1.dist-info/RECORD
