Metadata-Version: 2.1
Name: luftdatenpumpe
Version: 0.21.1
Summary: Process live and historical data from luftdaten.info, IRCELINE and OpenAQ. Filter by station-id, sensor-id and sensor-type, apply reverse geocoding, store into time-series and RDBMS databases, publish to MQTT, output as JSON, or visualize in Grafana.
Home-page: https://github.com/earthobservations/luftdatenpumpe
Author: Andreas Motl
Author-email: andreas.motl@panodata.org
License: AGPL 3, EUPL 1.2
Keywords: luftdaten.info irceline openaq air quality particulate matter pollution feinstaub luftdaten ogc sos sensor network observation opendata data acquisition transformation export geospatial temporal timeseries http rest json api rdbms sql mysql mosquitto mqtt openstreetmap nominatim postgis postgresql influxdb grafana 52north
Classifier: License :: OSI Approved :: GNU Affero General Public License v3
Classifier: License :: OSI Approved :: European Union Public Licence 1.2 (EUPL 1.2)
Classifier: Development Status :: 4 - Beta
Classifier: Environment :: Console
Classifier: Intended Audience :: Developers
Classifier: Intended Audience :: Education
Classifier: Intended Audience :: Information Technology
Classifier: Intended Audience :: Manufacturing
Classifier: Intended Audience :: Science/Research
Classifier: Intended Audience :: System Administrators
Classifier: Intended Audience :: Telecommunications Industry
Classifier: Programming Language :: Python
Classifier: Programming Language :: Python :: 3
Classifier: Programming Language :: Python :: 3.7
Classifier: Programming Language :: Python :: 3.8
Classifier: Programming Language :: Python :: 3.9
Classifier: Programming Language :: Python :: 3.10
Classifier: Programming Language :: Python :: 3.11
Classifier: Topic :: Communications
Classifier: Topic :: Database
Classifier: Topic :: Internet
Classifier: Topic :: Internet :: WWW/HTTP :: Indexing/Search
Classifier: Topic :: Scientific/Engineering :: Atmospheric Science
Classifier: Topic :: Scientific/Engineering :: GIS
Classifier: Topic :: Scientific/Engineering :: Human Machine Interfaces
Classifier: Topic :: Scientific/Engineering :: Information Analysis
Classifier: Topic :: Scientific/Engineering :: Interface Engine/Protocol Translator
Classifier: Topic :: Scientific/Engineering :: Visualization
Classifier: Topic :: Software Development :: Embedded Systems
Classifier: Topic :: Software Development :: Libraries
Classifier: Topic :: System :: Archiving
Classifier: Topic :: System :: Networking :: Monitoring
Classifier: Topic :: Text Processing
Classifier: Topic :: Utilities
Classifier: Operating System :: POSIX
Classifier: Operating System :: Unix
Classifier: Operating System :: MacOS
License-File: LICENSE
Requires-Dist: appdirs (<2)
Requires-Dist: docopt (<1)
Requires-Dist: munch (<3)
Requires-Dist: tqdm (<5)
Requires-Dist: requests (<3)
Requires-Dist: tablib[pandas] (<4)
Requires-Dist: py-openaq (<2)
Requires-Dist: requests-cache (<1)
Requires-Dist: dogpile.cache (<2)
Requires-Dist: redis (<5)
Requires-Dist: paho-mqtt (<2)
Requires-Dist: dataset (<2)
Requires-Dist: psycopg2-binary (<3)
Requires-Dist: GeoAlchemy2 (<1)
Requires-Dist: influxdb (<6)
Requires-Dist: SQLAlchemy (<1.4)
Requires-Dist: SQLAlchemy-Utils (<1)
Requires-Dist: rfc3339 (<7)
Requires-Dist: geohash2 (<2)
Requires-Dist: geopy (<2)
Requires-Dist: Jinja2 (<3)
Requires-Dist: MarkupSafe (<2.1)
Provides-Extra: test
Requires-Dist: pytest (<8,>=7) ; extra == 'test'
Requires-Dist: attrs ; extra == 'test'
Requires-Dist: pytest-cov (<4) ; extra == 'test'
